gradelib-0.2.0.dist-info/METADATA
gradelib-0.2.0.dist-info/WHEEL
gradelib-0.2.0.dist-info/license_files/LICENSE
gradelib/async_handler.py
gradelib/gradelib.pyi
gradelib/py.typed
gradelib/types.py
gradelib/__init__.py
gradelib/py.typed
gradelib/gradelib.cp313-win_amd64.pyd
gradelib-0.2.0.dist-info/RECORD
