Metadata-Version: 2.1
Name: gradelib
Version: 0.2.0
Classifier: Programming Language :: Rust
Classifier: Programming Language :: Python :: 3.9
Classifier: Programming Language :: Python :: 3.10
Classifier: Programming Language :: Python :: 3.11
Classifier: Programming Language :: Python :: 3.12
Classifier: Programming Language :: Python :: 3.13
Classifier: License :: OSI Approved :: MIT License
Classifier: License :: OSI Approved :: Apache Software License
Classifier: Operating System :: OS Independent
Classifier: Intended Audience :: Developers
Classifier: Topic :: Software Development :: Version Control :: Git
Requires-Dist: aiohttp >=3.11.18
Requires-Dist: maturin >=1.8.3
Requires-Dist: mkdocs >=1.6.1
Requires-Dist: mkdocs-awesome-pages-plugin >=2.10.1
Requires-Dist: mkdocs-material >=9.6.12
Requires-Dist: pip >=25.0.1
Requires-Dist: pyclean >=3.1.0
Requires-Dist: pytest >=7.0.0
Requires-Dist: pytest-asyncio >=0.21.0
Requires-Dist: toml >=0.10.2
Requires-Dist: nest_asyncio >=1.5.5
Requires-Dist: flask >=2.0.0 ; extra == 'web'
Provides-Extra: web
License-File: LICENSE
Summary: A library for managing github and taiga projects.
Author: Ben Meddeb <bmeddeb@asu.edu>
Author-email: Ben Meddeb <bmeddeb@asu.edu>
License: MIT OR Apache-2.0
Requires-Python: >=3.9
Project-URL: Homepage, https://bmeddeb.github.io/gradelib/
Project-URL: Repository, https://github.com/bmeddeb/gradelib
